LICENSE
README.txt
setup.py
django_repomgmt.egg-info/PKG-INFO
django_repomgmt.egg-info/SOURCES.txt
django_repomgmt.egg-info/dependency_links.txt
django_repomgmt.egg-info/requires.txt
django_repomgmt.egg-info/top_level.txt
repomgmt/__init__.py
repomgmt/admin.py
repomgmt/api.py
repomgmt/mock_data.py
repomgmt/models.py
repomgmt/tasks.py
repomgmt/tests.py
repomgmt/urls.py
repomgmt/utils.py
repomgmt/views.py
repomgmt/fixtures/test-ssh-key
repomgmt/fixtures/test-ssh-key.pub
repomgmt/fixtures/test_build.yaml
repomgmt/fixtures/test_cloud.yaml
repomgmt/fixtures/test_keypair.yaml
repomgmt/fixtures/test_series.yaml
repomgmt/management/__init__.py
repomgmt/management/processincoming.py
repomgmt/management/commands/__init__.py
repomgmt/management/commands/connect-to-node.py
repomgmt/management/commands/create-build-records.py
repomgmt/management/commands/freeze.py
repomgmt/management/commands/poll-upstreams.py
repomgmt/management/commands/process-build-queue.py
repomgmt/management/commands/processincoming.py
repomgmt/management/commands/refresh-tarball.py
repomgmt/management/commands/run-on-node.py
repomgmt/management/commands/set-repository-keyid.py
repomgmt/management/commands/sync-confs.py
repomgmt/management/commands/unfreeze.py
repomgmt/static/foo.txt
repomgmt/static/spinner.gif
repomgmt/static/bootstrap/css/bootstrap-responsive.css
repomgmt/static/bootstrap/css/bootstrap-responsive.min.css
repomgmt/static/bootstrap/css/bootstrap.css
repomgmt/static/bootstrap/css/bootstrap.min.css
repomgmt/static/bootstrap/img/glyphicons-halflings-white.png
repomgmt/static/bootstrap/img/glyphicons-halflings.png
repomgmt/static/bootstrap/js/bootstrap.js
repomgmt/static/bootstrap/js/bootstrap.min.js
repomgmt/templates/base.html
repomgmt/templates/buildd.puppet.pp.tmpl
repomgmt/templates/builders.html
repomgmt/templates/builds.html
repomgmt/templates/front.html
repomgmt/templates/new_repository_form.html
repomgmt/templates/new_series_form.html
repomgmt/templates/packages.html
repomgmt/templates/repositories.html
repomgmt/templates/seriess.html
repomgmt/templates/tarballs.html
repomgmt/templates/upstream_pkgs.html
repomgmt/templates/reprepro/create-build-records.sh.tmpl
