Metadata-Version: 1.1
Name: django-repomgmt
Version: 0.1.1
Summary: APT repo management, buildd, etc.
Home-page: http://github.com/sorenh/python-django-repomgmt
Author: Soren Hansen
Author-email: sorhanse@cisco.com
License: Apache 2.0
Keywords: django apt repository buildd
Platform: UNKNOWN
Classifier: Development Status :: 2 - Pre-Alpha
Classifier: Environment :: Web Environment
Classifier: Framework :: Django
Classifier: Intended Audience :: Developers
Classifier: License :: OSI Approved :: Apache Software License
Classifier: Operating System :: POSIX :: Linux
Classifier: Programming Language :: Python
Classifier: Topic :: Software Development
Classifier: Topic :: System :: Archiving :: Packaging
